README
setup.py
jsonprop/__init__.py
jsonprop/json_dict.py
jsonprop/json_encoder.py
jsonprop/json_field.py
jsonprop/json_property.py
jsonprop/test.py
jsonprop/test_json_field.py
jsonprop/test_kwargs.py
jsonprop/test_recursive.py
jsonprop.egg-info/PKG-INFO
jsonprop.egg-info/SOURCES.txt
jsonprop.egg-info/dependency_links.txt
jsonprop.egg-info/top_level.txt