Metadata-Version: 1.0
Name: jsonprop
Version: 0.0.5
Summary: A json serialization library for python.
Home-page: http://packages.python.org/jsonprop
Author: Dan Newcome
Author-email: dnewcome@circleup.com
License: BSD
Keywords: json serialization
Platform: UNKNOWN
Classifier: Development Status :: 3 - Alpha
Classifier: Topic :: Software Development :: Libraries
Classifier: License :: OSI Approved :: BSD License
